arxiv2bib/__init__.py
arxiv2bib/arxiv2bib
arxiv2bib/arxiv2bib.py
arxiv2bibpy-0.5.data/scripts/arxiv2bib
arxiv2bibpy-0.5.dist-info/METADATA
arxiv2bibpy-0.5.dist-info/WHEEL
arxiv2bibpy-0.5.dist-info/top_level.txt
arxiv2bibpy-0.5.dist-info/RECORD
