Metadata-Version: 2.1
Name: arxiv2bibpy
Version: 0.5
Summary: Search arxiv via api and save as bib
Home-page: https://github.com/code-fury/arxiv2bib
Author: Duong Nhu
Author-email: d.binhnhu@gmail.com
License: MIT
Keywords: arxiv,bibtext,bib
Platform: UNKNOWN
Requires-Dist: bs4 (==0.0.1)
Requires-Dist: bibtexparser (==1.1.0)
Requires-Dist: requests (==2.22.0)
